karrio/__init__.py
karrio/lib.py
karrio/references.py
karrio/sdk.py
karrio/addons/__init__.py
karrio/addons/label.py
karrio/addons/renderer.py
karrio/addons/fonts/Oswald-Regular.ttf
karrio/addons/fonts/Oswald-SemiBold.ttf
karrio/api/__init__.py
karrio/api/gateway.py
karrio/api/hooks.py
karrio/api/interface.py
karrio/api/mapper.py
karrio/api/proxy.py
karrio/core/__init__.py
karrio/core/errors.py
karrio/core/metadata.py
karrio/core/models.py
karrio/core/plugins.py
karrio/core/settings.py
karrio/core/units.py
karrio/core/utils/__init__.py
karrio/core/utils/caching.py
karrio/core/utils/config.py
karrio/core/utils/datetime.py
karrio/core/utils/dict.py
karrio/core/utils/enum.py
karrio/core/utils/functional.py
karrio/core/utils/helpers.py
karrio/core/utils/log.py
karrio/core/utils/logger.py
karrio/core/utils/number.py
karrio/core/utils/pipeline.py
karrio/core/utils/serializable.py
karrio/core/utils/soap.py
karrio/core/utils/string.py
karrio/core/utils/tracing.py
karrio/core/utils/transformer.py
karrio/core/utils/xml.py
karrio/mappers/__init__.py
karrio/plugins/__init__.py
karrio/providers/__init__.py
karrio/schemas/__init__.py
karrio/universal/__init__.py
karrio/universal/mappers/__init__.py
karrio/universal/mappers/rating_proxy.py
karrio/universal/mappers/shipping_proxy.py
karrio/universal/providers/__init__.py
karrio/universal/providers/rating/__init__.py
karrio/universal/providers/rating/rate.py
karrio/universal/providers/rating/utils.py
karrio/universal/providers/shipping/__init__.py
karrio/universal/providers/shipping/shipment.py
karrio/universal/providers/shipping/utils.py
karrio-2026.1.4.dist-info/METADATA
karrio-2026.1.4.dist-info/WHEEL
karrio-2026.1.4.dist-info/top_level.txt
karrio-2026.1.4.dist-info/RECORD
