Metadata-Version: 2.4
Name: karrio
Version: 2026.1.4
Summary: Multi-carrier shipping API integration with python
Author-email: karrio <hello@karrio.io>
License-Expression: LGPL-3.0
Project-URL: Homepage, https://github.com/karrioapi/karrio
Classifier: Intended Audience :: Developers
Classifier: Operating System :: OS Independent
Classifier: Programming Language :: Python :: 3
Requires-Python: >=3.11
Requires-Dist: attrs
Requires-Dist: jstruct
Requires-Dist: xmltodict
Requires-Dist: lxml
Requires-Dist: lxml-stubs
Requires-Dist: py-soap
Requires-Dist: Pillow
Requires-Dist: phonenumbers
Requires-Dist: python-barcode
Requires-Dist: PyPDF2
Requires-Dist: toml
Requires-Dist: loguru
